tornado_aws/__init__.py
tornado_aws/client.py
tornado_aws/config.py
tornado_aws/exceptions.py
tornado_aws/txml.py
tornado_aws-2.0.0.dist-info/LICENSE
tornado_aws-2.0.0.dist-info/METADATA
tornado_aws-2.0.0.dist-info/WHEEL
tornado_aws-2.0.0.dist-info/top_level.txt
tornado_aws-2.0.0.dist-info/zip-safe
tornado_aws-2.0.0.dist-info/RECORD
